cliff/__init__.py
cliff/_argparse.py
cliff/app.py
cliff/columns.py
cliff/command.py
cliff/commandmanager.py
cliff/complete.py
cliff/display.py
cliff/help.py
cliff/hooks.py
cliff/interactive.py
cliff/lister.py
cliff/py.typed
cliff/show.py
cliff/sphinxext.py
cliff/utils.py
cliff/formatters/__init__.py
cliff/formatters/base.py
cliff/formatters/commaseparated.py
cliff/formatters/json_format.py
cliff/formatters/shell.py
cliff/formatters/table.py
cliff/formatters/value.py
cliff/formatters/yaml_format.py
cliff/tests/__init__.py
cliff/tests/base.py
cliff/tests/test__argparse.py
cliff/tests/test_app.py
cliff/tests/test_columns.py
cliff/tests/test_command.py
cliff/tests/test_command_hooks.py
cliff/tests/test_commandmanager.py
cliff/tests/test_complete.py
cliff/tests/test_formatters_csv.py
cliff/tests/test_formatters_json.py
cliff/tests/test_formatters_shell.py
cliff/tests/test_formatters_table.py
cliff/tests/test_formatters_value.py
cliff/tests/test_formatters_yaml.py
cliff/tests/test_help.py
cliff/tests/test_interactive.py
cliff/tests/test_lister.py
cliff/tests/test_show.py
cliff/tests/test_sphinxext.py
cliff/tests/test_utils.py
cliff/tests/utils.py
cliff-4.13.1.dist-info/licenses/AUTHORS
cliff-4.13.1.dist-info/licenses/LICENSE
cliff-4.13.1.dist-info/METADATA
cliff-4.13.1.dist-info/WHEEL
cliff-4.13.1.dist-info/entry_points.txt
cliff-4.13.1.dist-info/pbr.json
cliff-4.13.1.dist-info/top_level.txt
cliff-4.13.1.dist-info/RECORD
