Metadata-Version: 2.4
Name: cliff
Version: 4.13.1
Summary: Command Line Interface Formulation Framework
Author-email: OpenStack <openstack-discuss@lists.openstack.org>
License: Apache-2.0
Project-URL: Homepage, https://docs.openstack.org/cliff/
Project-URL: Repository, https://opendev.org/openstack/cliff/
Classifier: Development Status :: 5 - Production/Stable
Classifier: Environment :: Console
Classifier: Intended Audience :: Developers
Classifier: License :: OSI Approved :: Apache Software License
Classifier: Operating System :: POSIX :: Linux
Classifier: Programming Language :: Python
Classifier: Programming Language :: Python :: 3
Classifier: Programming Language :: Python :: 3.10
Classifier: Programming Language :: Python :: 3.11
Classifier: Programming Language :: Python :: 3.12
Classifier: Programming Language :: Python :: 3.13
Requires-Python: >=3.10
License-File: LICENSE
Requires-Dist: autopage>=0.4.0
Requires-Dist: cmd2>=1.0.0
Requires-Dist: PrettyTable>=0.7.2
Requires-Dist: stevedore>=5.6.0
Requires-Dist: PyYAML>=3.12
Dynamic: license-file
Dynamic: requires-dist
